soyspacing/__init__.py
soyspacing/hangle.py
soyspacing/countbase/__init__.py
soyspacing/countbase/_countbase.py
soyspacing-1.0.17.dist-info/METADATA
soyspacing-1.0.17.dist-info/WHEEL
soyspacing-1.0.17.dist-info/top_level.txt
soyspacing-1.0.17.dist-info/RECORD
