Metadata-Version: 2.1
Name: soyspacing
Version: 1.0.17
Summary: Spacing Error Correction Tools
Home-page: https://github.com/lovit/soyspacing
Author: Lovit & ScatterLab
Author-email: soy.lovit@gmail.com
License: UNKNOWN
Keywords: Space-error-correction,Korean-spacing,Korean,Natural-Language-Processing
Platform: UNKNOWN
Classifier: Programming Language :: Python :: 3.6
Classifier: License :: OSI Approved :: GNU General Public License v3 (GPLv3)
Classifier: Operating System :: OS Independent
Requires-Dist: numpy (>=1.12.0)
